hydragram/__init__.py
hydragram/client.py
hydragram/filters.py
hydragram/fonts.py
hydragram/handler.py
hydragram/keyboard.py
hydragram/resolve_peer.py
hydragram-3.2.0.dist-info/licenses/LICENSE
hydragram-3.2.0.dist-info/METADATA
hydragram-3.2.0.dist-info/WHEEL
hydragram-3.2.0.dist-info/top_level.txt
hydragram-3.2.0.dist-info/RECORD
