Metadata-Version: 2.4
Name: hydragram
Version: 3.2.0
Summary: An enhanced Pyrogram-like filter and handler system using Pyrogram.
Home-page: https://github.com/Endtrz/hydragram
Author: Endtrz
Author-email: endtrz@gmail.com
Classifier: Programming Language :: Python :: 3
Classifier: License :: OSI Approved :: MIT License
Classifier: Operating System :: OS Independent
Requires-Python: >=3.8
License-File: LICENSE
Requires-Dist: pyrogram>=2.0.106
Requires-Dist: tgcrypto>=1.2.5
Requires-Dist: kurigram
Dynamic: author
Dynamic: author-email
Dynamic: classifier
Dynamic: description
Dynamic: description-content-type
Dynamic: home-page
Dynamic: license-file
Dynamic: requires-dist
Dynamic: requires-python
Dynamic: summary
